{
  "main": {
    "id": "ef57a17f4d34833d",
    "type": "split",
    "children": [
      {
        "id": "6ab9b3701d091b33",
        "type": "tabs",
        "children": [
          {
            "id": "c8c6c5ae9134e381",
            "type": "leaf",
            "state": {
              "type": "markdown",
              "state": {
                "file": "Mon-yu/Treasure/Gjallarhorn.md",
                "mode": "source",
                "source": false
              }
            }
          },
          {
            "id": "460fb8b656cfadbe",
            "type": "leaf",
            "state": {
              "type": "markdown",
              "state": {
                "file": "Mon-yu/_DAILY/_OBSERVATIONS.md",
                "mode": "source",
                "source": false
              }
            },
            "group": "c37fdc38b21fd405"
          }
        ],
        "currentTab": 1
      },
      {
        "id": "9fb3d25831ae3703",
        "type": "tabs",
        "children": [
          {
            "id": "2d62cbb01af08bbb",
            "type": "leaf",
            "state": {
              "type": "markdown",
              "state": {
                "file": "Mon-yu/_DAILY/_OBSERVATIONS.md",
                "mode": "preview",
                "source": false
              }
            },
            "group": "c37fdc38b21fd405"
          }
        ]
      }
    ],
    "direction": "vertical"
  },
  "left": {
    "id": "b7b979370baac9e0",
    "type": "split",
    "children": [
      {
        "id": "da60b90d3c2ec7b0",
        "type": "tabs",
        "children": [
          {
            "id": "e21428d8b367f646",
            "type": "leaf",
            "state": {
              "type": "file-explorer",
              "state": {
                "sortOrder": "alphabetical"
              }
            }
          },
          {
            "id": "6c70dafb4dcdaa43",
            "type": "leaf",
            "state": {
              "type": "search",
              "state": {
                "query": "",
                "matchingCase": false,
                "explainSearch": false,
                "collapseAll": false,
                "extraContext": false,
                "sortOrder": "alphabetical"
              }
            }
          },
          {
            "id": "6c888c1b2c35735e",
            "type": "leaf",
            "state": {
              "type": "bookmarks",
              "state": {}
            }
          }
        ]
      }
    ],
    "direction": "horizontal",
    "width": 321.5
  },
  "right": {
    "id": "a4fcf206dc3a1ffb",
    "type": "split",
    "children": [
      {
        "id": "3b9e720e565a06e4",
        "type": "tabs",
        "children": [
          {
            "id": "ba4a8e89135b2085",
            "type": "leaf",
            "state": {
              "type": "backlink",
              "state": {
                "file": "Mon-yu/_DAILY/_OBSERVATIONS.md",
                "collapseAll": false,
                "extraContext": false,
                "sortOrder": "alphabetical",
                "showSearch": false,
                "searchQuery": "",
                "backlinkCollapsed": false,
                "unlinkedCollapsed": true
              }
            }
          },
          {
            "id": "d582b6e994fc37ec",
            "type": "leaf",
            "state": {
              "type": "outgoing-link",
              "state": {
                "file": "Mon-yu/_DAILY/_OBSERVATIONS.md",
                "linksCollapsed": false,
                "unlinkedCollapsed": true
              }
            }
          },
          {
            "id": "bbad6ac9c8ea4251",
            "type": "leaf",
            "state": {
              "type": "tag",
              "state": {
                "sortOrder": "frequency",
                "useHierarchy": true
              }
            }
          },
          {
            "id": "59fb5b26a789a764",
            "type": "leaf",
            "state": {
              "type": "outline",
              "state": {
                "file": "Mon-yu/_DAILY/_OBSERVATIONS.md"
              }
            }
          },
          {
            "id": "6824a0a2468ccd9e",
            "type": "leaf",
            "state": {
              "type": "git-view",
              "state": {}
            }
          }
        ],
        "currentTab": 4
      }
    ],
    "direction": "horizontal",
    "width": 345.5
  },
  "left-ribbon": {
    "hiddenItems": {
      "switcher:Open quick switcher": false,
      "graph:Open graph view": false,
      "canvas:Create new canvas": false,
      "daily-notes:Open today's daily note": false,
      "templates:Insert template": false,
      "command-palette:Open command palette": false
    }
  },
  "active": "460fb8b656cfadbe",
  "lastOpenFiles": [
    "Mon-yu/_DAILY/_QUESTIONS.md",
    "Mon-yu/_DAILY/_OBSERVATIONS.md",
    "Mon-yu/Treasure/Clanniebe.md",
    "Mon-yu/Treasure/Mjolnir.md",
    "Mon-yu/Treasure/Mistilteinn.md",
    "Mon-yu/Treasure/Gjallarhorn.md",
    "Mon-yu/Treasure/Laevateinn.md",
    "Mon-yu/Terminology/Clan Skill.md",
    "Mon-yu/People/Surtr.md",
    "Mon-yu/_DAILY/2023-11-23.md",
    "Mon-yu/_DAILY/2023-11-22.md",
    "Mon-yu/People/Devil Kings.md",
    "Mon-yu/Places/Magiheim.md",
    "Mon-yu/People/Hel.md",
    "Mon-yu/Places/Bonheim.md",
    "Mon-yu/Places/Demiheim.md",
    "Mon-yu/Places/Einheim.md",
    "Mon-yu/Field Guide.md",
    "Mon-yu/People/Freyr.md",
    "Mon-yu/People/Fenrir.md",
    "README.md",
    "Mon-yu/README.md",
    "Undernauts/README.md",
    "Undernauts/Undernauts.md",
    "Undernauts/Yomiten.md",
    "Mon-yu/Mon-yu.md",
    "Experience Inc/Mon-yu/Untitled",
    "Experience Inc/Mon-yu/Untitled.canvas",
    "Templates",
    "Mon-yu/Classes",
    "Mon-yu/Treasure",
    "Mon-yu/Things",
    "Mon-yu/Groups",
    "Mon-yu/Terminology",
    "Mon-yu/Places",
    "Mon-yu/People",
    "Experience Inc/Mon-yu/Help",
    "Experience Inc/Undernauts/Untitled.canvas",
    "Untitled.canvas"
  ]
}